threshold_finder/__init__.py
threshold_finder/finder.py
threshold_finder-0.1.4.dist-info/WHEEL
threshold_finder-0.1.4.dist-info/METADATA
threshold_finder-0.1.4.dist-info/RECORD
